the_guide/__init__.py
the_guide/asgi.py
the_guide/celery.py
the_guide/settings/__init__.py
the_guide/settings/base.py
the_guide/settings/celery.py
the_guide/settings/dev.py
the_guide/settings/prod.py
the_guide/tests/test_views.py
the_guide/urls.py
the_guide/views.py
the_guide/wsgi.py
the_guide-0.1.36.dist-info/METADATA
the_guide-0.1.36.dist-info/WHEEL
the_guide-0.1.36.dist-info/RECORD
